{
    "testcases": {
        "memory": {
            "DDR": {
                "global_config": {
                    "disable_prewrite": true,
                    "test_sequence": [

                    
                        { "duration": 20, "mode": "only_wr", "wr_rate": 1   },
                        { "duration": 20, "mode": "only_wr", "wr_rate": 2   },
                        { "duration": 20, "mode": "only_wr", "wr_rate": 3   },
                        { "duration": 20, "mode": "only_wr", "wr_rate": 4   },
                        { "duration": 20, "mode": "only_wr", "wr_rate": 5   },
                        { "duration": 20, "mode": "only_wr", "wr_rate": 6   },
                        { "duration": 20, "mode": "only_wr", "wr_rate": 7   },
                        { "duration": 20, "mode": "only_wr", "wr_rate": 8   },
                        { "duration": 20, "mode": "only_wr", "wr_rate": 9   },
                        { "duration": 20, "mode": "only_wr", "wr_rate": 10  },
                        { "duration": 20, "mode": "only_wr", "wr_rate": 11  },
                        { "duration": 20, "mode": "only_wr", "wr_rate": 12  },
                        { "duration": 20, "mode": "only_wr", "wr_rate": 13  },
                        { "duration": 20, "mode": "only_wr", "wr_rate": 14  },
                        { "duration": 20, "mode": "only_wr", "wr_rate": 15  },
                        { "duration": 20, "mode": "only_wr", "wr_rate": 16  },
                        { "duration": 20, "mode": "only_wr", "wr_rate": 17  },
                        { "duration": 20, "mode": "only_wr", "wr_rate": 18  },
                        { "duration": 20, "mode": "only_wr", "wr_rate": 19  },
                        { "duration": 20, "mode": "only_wr", "wr_rate": 20  },
                        { "duration": 20, "mode": "only_wr", "wr_rate": 21  },
                        { "duration": 20, "mode": "only_wr", "wr_rate": 22  },
                        { "duration": 20, "mode": "only_wr", "wr_rate": 23  },
                        { "duration": 20, "mode": "only_wr", "wr_rate": 24  },
                        { "duration": 20, "mode": "only_wr", "wr_rate": 25  },
                        { "duration": 20, "mode": "only_wr", "wr_rate": 26  },
                        { "duration": 20, "mode": "only_wr", "wr_rate": 27  },
                        { "duration": 20, "mode": "only_wr", "wr_rate": 28  },
                        { "duration": 20, "mode": "only_wr", "wr_rate": 29  },
                        { "duration": 20, "mode": "only_wr", "wr_rate": 30  },
                        { "duration": 20, "mode": "only_wr", "wr_rate": 31  },
                        { "duration": 20, "mode": "only_wr", "wr_rate": 32  },
                        { "duration": 20, "mode": "only_wr", "wr_rate": 33  },
                        { "duration": 20, "mode": "only_wr", "wr_rate": 34  },
                        { "duration": 20, "mode": "only_wr", "wr_rate": 35  },
                        { "duration": 20, "mode": "only_wr", "wr_rate": 36  },
                        { "duration": 20, "mode": "only_wr", "wr_rate": 37  },
                        { "duration": 20, "mode": "only_wr", "wr_rate": 38  },
                        { "duration": 20, "mode": "only_wr", "wr_rate": 39  },
                        { "duration": 20, "mode": "only_wr", "wr_rate": 40  },
                        { "duration": 20, "mode": "only_wr", "wr_rate": 41  },
                        { "duration": 20, "mode": "only_wr", "wr_rate": 42  },
                        { "duration": 20, "mode": "only_wr", "wr_rate": 43  },
                        { "duration": 20, "mode": "only_wr", "wr_rate": 44  },
                        { "duration": 20, "mode": "only_wr", "wr_rate": 45  },
                        { "duration": 20, "mode": "only_wr", "wr_rate": 46  },
                        { "duration": 20, "mode": "only_wr", "wr_rate": 47  },
                        { "duration": 20, "mode": "only_wr", "wr_rate": 48  },
                        { "duration": 20, "mode": "only_wr", "wr_rate": 49  },
                        { "duration": 20, "mode": "only_wr", "wr_rate": 50  },
                        { "duration": 20, "mode": "only_wr", "wr_rate": 51  },
                        { "duration": 20, "mode": "only_wr", "wr_rate": 52  },
                        { "duration": 20, "mode": "only_wr", "wr_rate": 53  },
                        { "duration": 20, "mode": "only_wr", "wr_rate": 54  },
                        { "duration": 20, "mode": "only_wr", "wr_rate": 55  },
                        { "duration": 20, "mode": "only_wr", "wr_rate": 56  },
                        { "duration": 20, "mode": "only_wr", "wr_rate": 57  },
                        { "duration": 20, "mode": "only_wr", "wr_rate": 58  },
                        { "duration": 20, "mode": "only_wr", "wr_rate": 59  },
                        { "duration": 20, "mode": "only_wr", "wr_rate": 60  },
                        { "duration": 20, "mode": "only_wr", "wr_rate": 61  },
                        { "duration": 20, "mode": "only_wr", "wr_rate": 62  },
                        { "duration": 20, "mode": "only_wr", "wr_rate": 63  },
                        { "duration": 20, "mode": "only_wr", "wr_rate": 64  },
                        { "duration": 20, "mode": "only_wr", "wr_rate": 65  },
                        { "duration": 20, "mode": "only_wr", "wr_rate": 66  },
                        { "duration": 20, "mode": "only_wr", "wr_rate": 67  },
                        { "duration": 20, "mode": "only_wr", "wr_rate": 68  },
                        { "duration": 20, "mode": "only_wr", "wr_rate": 69  },
                        { "duration": 20, "mode": "only_wr", "wr_rate": 70  },
                        { "duration": 20, "mode": "only_wr", "wr_rate": 71  },
                        { "duration": 20, "mode": "only_wr", "wr_rate": 72  },
                        { "duration": 20, "mode": "only_wr", "wr_rate": 73  },
                        { "duration": 20, "mode": "only_wr", "wr_rate": 74  },
                        { "duration": 20, "mode": "only_wr", "wr_rate": 75  },
                        { "duration": 20, "mode": "only_wr", "wr_rate": 76  },
                        { "duration": 20, "mode": "only_wr", "wr_rate": 77  },
                        { "duration": 20, "mode": "only_wr", "wr_rate": 78  },
                        { "duration": 20, "mode": "only_wr", "wr_rate": 79  },
                        { "duration": 20, "mode": "only_wr", "wr_rate": 80  },
                        { "duration": 20, "mode": "only_wr", "wr_rate": 81  },
                        { "duration": 20, "mode": "only_wr", "wr_rate": 82  },
                        { "duration": 20, "mode": "only_wr", "wr_rate": 83  },
                        { "duration": 20, "mode": "only_wr", "wr_rate": 84  },
                        { "duration": 20, "mode": "only_wr", "wr_rate": 85  },
                        { "duration": 20, "mode": "only_wr", "wr_rate": 86  },
                        { "duration": 20, "mode": "only_wr", "wr_rate": 87  },
                        { "duration": 20, "mode": "only_wr", "wr_rate": 88  },
                        { "duration": 20, "mode": "only_wr", "wr_rate": 89  },
                        { "duration": 20, "mode": "only_wr", "wr_rate": 90  },
                        { "duration": 20, "mode": "only_wr", "wr_rate": 91  },
                        { "duration": 20, "mode": "only_wr", "wr_rate": 92  },
                        { "duration": 20, "mode": "only_wr", "wr_rate": 93  },
                        { "duration": 20, "mode": "only_wr", "wr_rate": 94  },
                        { "duration": 20, "mode": "only_wr", "wr_rate": 95  },
                        { "duration": 20, "mode": "only_wr", "wr_rate": 96  },
                        { "duration": 20, "mode": "only_wr", "wr_rate": 97  },
                        { "duration": 20, "mode": "only_wr", "wr_rate": 98  },
                        { "duration": 20, "mode": "only_wr", "wr_rate": 99  },
                        { "duration": 20, "mode": "only_wr", "wr_rate": 100 }
                   ]
                }
            }
        }
    }
}